README.txt
setup.py
svnignore.sh
docs/HISTORY.txt
src/collective/__init__.py
src/collective.generic.skel.egg-info/PKG-INFO
src/collective.generic.skel.egg-info/SOURCES.txt
src/collective.generic.skel.egg-info/dependency_links.txt
src/collective.generic.skel.egg-info/entry_points.txt
src/collective.generic.skel.egg-info/namespace_packages.txt
src/collective.generic.skel.egg-info/requires.txt
src/collective.generic.skel.egg-info/top_level.txt
src/collective/generic/__init__.py
src/collective/generic/skel/__init__.py
src/collective/generic/skel/common/__init__.py
src/collective/generic/skel/common/package.py
src/collective/generic/skel/common/tmpl/README.txt
src/collective/generic/skel/common/tmpl/bootstrap.py
src/collective/generic/skel/common/tmpl/buildout.cfg_tmpl
src/collective/generic/skel/common/tmpl/setup.cfg
src/collective/generic/skel/common/tmpl/setup.py_tmpl
src/collective/generic/skel/common/tmpl/docs/HISTORY.txt_tmpl
src/collective/generic/skel/common/tmpl/docs/INSTALL.txt_tmpl
src/collective/generic/skel/common/tmpl/docs/LICENSE.GPL
src/collective/generic/skel/common/tmpl/docs/LICENSE.txt_tmpl
src/collective/generic/skel/common/tmpl/src/+namespace+/__init__.py
src/collective/generic/skel/common/tmpl/src/+namespace+/+nested_namespace+/__init__.py
src/collective/generic/skel/common/tmpl/src/+namespace+/+nested_namespace+/+project_name+/+project_name+.py
src/collective/generic/skel/common/tmpl/src/+namespace+/+nested_namespace+/+project_name+/__init__.py
src/collective/generic/skel/policy/__init__.py
src/collective/generic/skel/policy/package.py
src/collective/generic/skel/policy/tmpl/+namespace++ndot++nested_namespace+.+project_name+/README.txt
src/collective/generic/skel/policy/tmpl/+namespace++ndot++nested_namespace+.+project_name+/setup.cfg
src/collective/generic/skel/policy/tmpl/+namespace++ndot++nested_namespace+.+project_name+/setup.py_tmpl
src/collective/generic/skel/policy/tmpl/+namespace++ndot++nested_namespace+.+project_name+/version.txt
src/collective/generic/skel/policy/tmpl/+namespace++ndot++nested_namespace+.+project_name+/docs/HISTORY.txt_tmpl
src/collective/generic/skel/policy/tmpl/+namespace++ndot++nested_namespace+.+project_name+/docs/INSTALL.txt_tmpl
src/collective/generic/skel/policy/tmpl/+namespace++ndot++nested_namespace+.+project_name+/docs/LICENSE.GPL
