Metadata-Version: 1.0
Name: collective.generic.skel
Version: 0.1.0
Summary: PasteScript templates for collective.generic suite sponsorised by Makina Corpus
Home-page: http://makina-corpus.com
Author: Mathieu Pasquet / Jean-Philippe Camguilhem
Author-email: kiorky@cryptelium.net, jpc@makina-corpus.com
License: GPL
Keywords: paste templates
Platform: UNKNOWN
Classifier: Programming Language :: Python
Classifier: Framework :: Paste
Classifier: Framework :: Plone
Classifier: Topic :: Software Development :: Libraries :: Python Modules
